garmin_health_data/__init__.py
garmin_health_data/__version__.py
garmin_health_data/auth.py
garmin_health_data/cli.py
garmin_health_data/constants.py
garmin_health_data/db.py
garmin_health_data/extractor.py
garmin_health_data/models.py
garmin_health_data/processor.py
garmin_health_data/processor_helpers.py
garmin_health_data/tables.ddl
garmin_health_data/utils.py
garmin_health_data-2.0.2.dist-info/licenses/LICENSE
garmin_health_data-2.0.2.dist-info/METADATA
garmin_health_data-2.0.2.dist-info/WHEEL
garmin_health_data-2.0.2.dist-info/entry_points.txt
garmin_health_data-2.0.2.dist-info/top_level.txt
garmin_health_data-2.0.2.dist-info/RECORD
